conv_pca/__init__.py
conv_pca/conv_ae.py
conv_pca/conv_pca.py
convPCA-0.0.1.dist-info/LICENSE
convPCA-0.0.1.dist-info/METADATA
convPCA-0.0.1.dist-info/WHEEL
convPCA-0.0.1.dist-info/top_level.txt
convPCA-0.0.1.dist-info/RECORD
