Metadata-Version: 2.1
Name: convPCA
Version: 0.0.1
Summary: Convolutional version of PCA using Power Iteration, FastICA and Autoencoders.
Home-page: https://github.com/davidaknowles/convPCA
Author: David A Knowles
Author-email: dak2173@columbia.edu
License: UNKNOWN
Project-URL: Bug Tracker, https://github.com/davidaknowles/convPCA/issues
Platform: UNKNOWN
Classifier: Programming Language :: Python :: 3
Classifier: License :: OSI Approved :: MIT License
Classifier: Operating System :: OS Independent
Requires-Python: >=3.6
License-File: LICENSE
